{
  "concerns": [
    { "id": "local-store", "nameJa": "local-store", "nameEn": "local-store" },
    { "id": "issue", "nameJa": "Issue", "nameEn": "Issue" },
    { "id": "src-main", "nameJa": "main", "nameEn": "main" },
    { "id": "src-preload", "nameJa": "preload", "nameEn": "preload" },
    { "id": "src-shared", "nameJa": "shared", "nameEn": "shared" },
    { "id": "src-adapters", "nameJa": "adapters", "nameEn": "adapters" },
    { "id": "src-bootstrap", "nameJa": "bootstrap", "nameEn": "bootstrap" },
    { "id": "src-catalog", "nameJa": "catalog", "nameEn": "catalog" },
    { "id": "src-components", "nameJa": "components", "nameEn": "components" },
    { "id": "src-contracts", "nameJa": "contracts", "nameEn": "contracts" },
    { "id": "src-editor", "nameJa": "editor", "nameEn": "editor" },
    { "id": "src-interactions", "nameJa": "interactions", "nameEn": "interactions" },
    { "id": "src-layouts", "nameJa": "layouts", "nameEn": "layouts" },
    { "id": "src-screens", "nameJa": "screens", "nameEn": "screens" },
    { "id": "src-spec", "nameJa": "spec", "nameEn": "spec" },
    { "id": "src-state", "nameJa": "state", "nameEn": "state" }
  ],
  "tools": [{ "id": "ui-spec-editor", "nameJa": "ui-spec-editor", "nameEn": "ui-spec-editor" }],
  "screens": [
    {
      "id": "main-screen",
      "nameJa": "メイン画面",
      "nameEn": "Main Screen",
      "viewports": {
        "desktop": {
          "id": "desktop",
          "components": [
            {
              "id": "page-root",
              "nameJa": "ページ",
              "nameEn": "pageRoot",
              "type": "Page",
              "frame": { "x": 0, "y": 0, "w": 120, "h": 120 },
              "props": {
                "title": "UI Spec Editor",
                "surface": "canvas",
                "textAlign": "left",
                "fontSize": 18,
                "color": "#cccccc"
              },
              "editorMetadata": { "note": "Top-level screen container." }
            },
            {
              "id": "header-root",
              "nameJa": "ヘッダー",
              "nameEn": "header",
              "type": "Header",
              "parentId": "page-root",
              "frame": { "x": 6, "y": 6, "w": 108, "h": 14 },
              "props": {
                "title": "UI Spec Editor\nShared visual language for AI collaboration",
                "textAlign": "left",
                "fontSize": 18,
                "color": "#cccccc"
              },
              "editorMetadata": { "note": "" }
            },
            {
              "id": "action-footer",
              "nameJa": "フッター",
              "nameEn": "actionFooter",
              "type": "Footer",
              "parentId": "page-root",
              "frame": { "x": 6, "y": 102, "w": 108, "h": 12 },
              "props": { "tone": "default" },
              "editorMetadata": { "note": "" }
            },
            {
              "id": "save-button",
              "nameJa": "保存ボタン",
              "nameEn": "saveButton",
              "type": "Button",
              "parentId": "action-footer",
              "frame": { "x": 86, "y": 104, "w": 22, "h": 7 },
              "props": {
                "title": "Save Spec",
                "emphasis": "primary",
                "textAlign": "center",
                "fontSize": 14,
                "color": "#ffffff"
              },
              "editorMetadata": { "note": "" }
            }
          ]
        },
        "tablet": { "id": "tablet", "components": [] },
        "mobile": { "id": "mobile", "components": [] }
      }
    }
  ],
  "specNodes": [
    {
      "id": "file:ui:spec-document",
      "kind": "issue",
      "titleJa": "spec-document.json",
      "titleEn": "spec-document.json",
      "parentId": "concern-node:local-store",
      "order": 0,
      "doc": { "constraints": [], "goals": [], "hints": [], "todos": [] },
      "links": [
        {
          "id": "link:ui:spec-document",
          "kind": "file",
          "label": "spec-document.json",
          "target": "ui/spec-document.json"
        }
      ]
    },
    {
      "id": "file:issue:smoke",
      "kind": "issue",
      "titleJa": "electron-smoke.spec.ts",
      "titleEn": "electron-smoke.spec.ts",
      "parentId": "concern-node:issue",
      "order": 0,
      "doc": { "constraints": [], "goals": [], "hints": [], "todos": [] },
      "links": [
        {
          "id": "link:issue:smoke",
          "kind": "file",
          "label": "electron-smoke.spec.ts",
          "target": "tests/ui/electron-smoke.spec.ts"
        }
      ]
    },
    {
      "id": "file:issue:update",
      "kind": "issue",
      "titleJa": "electron-update.spec.ts",
      "titleEn": "electron-update.spec.ts",
      "parentId": "concern-node:issue",
      "order": 1,
      "doc": { "constraints": [], "goals": [], "hints": [], "todos": [] },
      "links": [
        {
          "id": "link:issue:update",
          "kind": "file",
          "label": "electron-update.spec.ts",
          "target": "tests/ui/electron-update.spec.ts"
        }
      ]
    },
    {
      "id": "file:issue:release-update",
      "kind": "issue",
      "titleJa": "electron-release-update.spec.ts",
      "titleEn": "electron-release-update.spec.ts",
      "parentId": "concern-node:issue",
      "order": 2,
      "doc": { "constraints": [], "goals": [], "hints": [], "todos": [] },
      "links": [
        {
          "id": "link:issue:release-update",
          "kind": "file",
          "label": "electron-release-update.spec.ts",
          "target": "tests/ui/electron-release-update.spec.ts"
        }
      ]
    },
    {
      "id": "file:main:index",
      "kind": "issue",
      "titleJa": "index.ts",
      "titleEn": "index.ts",
      "parentId": "concern-node:src-main",
      "order": 0,
      "doc": { "constraints": [], "goals": [], "hints": [], "todos": [] },
      "links": [
        {
          "id": "link:main:index",
          "kind": "file",
          "label": "index.ts",
          "target": "src/main/index.ts"
        }
      ]
    },
    {
      "id": "file:main:spec-document",
      "kind": "issue",
      "titleJa": "spec-document.ts",
      "titleEn": "spec-document.ts",
      "parentId": "concern-node:src-main",
      "order": 1,
      "doc": { "constraints": [], "goals": [], "hints": [], "todos": [] },
      "links": [
        {
          "id": "link:main:spec-document",
          "kind": "file",
          "label": "spec-document.ts",
          "target": "src/main/spec-document.ts"
        }
      ]
    },
    {
      "id": "file:main:ui-shell-settings",
      "kind": "issue",
      "titleJa": "ui-shell-settings.ts",
      "titleEn": "ui-shell-settings.ts",
      "parentId": "concern-node:src-main",
      "order": 2,
      "doc": { "constraints": [], "goals": [], "hints": [], "todos": [] },
      "links": [
        {
          "id": "link:main:ui-shell-settings",
          "kind": "file",
          "label": "ui-shell-settings.ts",
          "target": "src/main/ui-shell-settings.ts"
        }
      ]
    },
    {
      "id": "file:main:updater",
      "kind": "issue",
      "titleJa": "updater.ts",
      "titleEn": "updater.ts",
      "parentId": "concern-node:src-main",
      "order": 3,
      "doc": { "constraints": [], "goals": [], "hints": [], "todos": [] },
      "links": [
        {
          "id": "link:main:updater",
          "kind": "file",
          "label": "updater.ts",
          "target": "src/main/updater.ts"
        }
      ]
    },
    {
      "id": "file:preload:index",
      "kind": "issue",
      "titleJa": "index.ts",
      "titleEn": "index.ts",
      "parentId": "concern-node:src-preload",
      "order": 0,
      "doc": { "constraints": [], "goals": [], "hints": [], "todos": [] },
      "links": [
        {
          "id": "link:preload:index",
          "kind": "file",
          "label": "index.ts",
          "target": "src/preload/index.ts"
        }
      ]
    },
    {
      "id": "file:shared:app-metadata",
      "kind": "issue",
      "titleJa": "app-metadata.ts",
      "titleEn": "app-metadata.ts",
      "parentId": "concern-node:src-shared",
      "order": 0,
      "doc": { "constraints": [], "goals": [], "hints": [], "todos": [] },
      "links": [
        {
          "id": "link:shared:app-metadata",
          "kind": "file",
          "label": "app-metadata.ts",
          "target": "src/shared/app-metadata.ts"
        }
      ]
    },
    {
      "id": "file:shared:runtime-ipc",
      "kind": "issue",
      "titleJa": "runtime-ipc.ts",
      "titleEn": "runtime-ipc.ts",
      "parentId": "concern-node:src-shared",
      "order": 1,
      "doc": { "constraints": [], "goals": [], "hints": [], "todos": [] },
      "links": [
        {
          "id": "link:shared:runtime-ipc",
          "kind": "file",
          "label": "runtime-ipc.ts",
          "target": "src/shared/runtime-ipc.ts"
        }
      ]
    },
    {
      "id": "file:shared:runtime-snapshot",
      "kind": "issue",
      "titleJa": "runtime-snapshot.ts",
      "titleEn": "runtime-snapshot.ts",
      "parentId": "concern-node:src-shared",
      "order": 2,
      "doc": { "constraints": [], "goals": [], "hints": [], "todos": [] },
      "links": [
        {
          "id": "link:shared:runtime-snapshot",
          "kind": "file",
          "label": "runtime-snapshot.ts",
          "target": "src/shared/runtime-snapshot.ts"
        }
      ]
    },
    {
      "id": "file:shared:spec-document",
      "kind": "issue",
      "titleJa": "spec-document.ts",
      "titleEn": "spec-document.ts",
      "parentId": "concern-node:src-shared",
      "order": 3,
      "doc": { "constraints": [], "goals": [], "hints": [], "todos": [] },
      "links": [
        {
          "id": "link:shared:spec-document",
          "kind": "file",
          "label": "spec-document.ts",
          "target": "src/shared/spec-document.ts"
        }
      ]
    },
    {
      "id": "file:shared:spec-document-ipc",
      "kind": "issue",
      "titleJa": "spec-document-ipc.ts",
      "titleEn": "spec-document-ipc.ts",
      "parentId": "concern-node:src-shared",
      "order": 4,
      "doc": { "constraints": [], "goals": [], "hints": [], "todos": [] },
      "links": [
        {
          "id": "link:shared:spec-document-ipc",
          "kind": "file",
          "label": "spec-document-ipc.ts",
          "target": "src/shared/spec-document-ipc.ts"
        }
      ]
    },
    {
      "id": "file:shared:surface-context",
      "kind": "issue",
      "titleJa": "surface-context.ts",
      "titleEn": "surface-context.ts",
      "parentId": "concern-node:src-shared",
      "order": 5,
      "doc": { "constraints": [], "goals": [], "hints": [], "todos": [] },
      "links": [
        {
          "id": "link:shared:surface-context",
          "kind": "file",
          "label": "surface-context.ts",
          "target": "src/shared/surface-context.ts"
        }
      ]
    },
    {
      "id": "file:shared:ui-shell-settings",
      "kind": "issue",
      "titleJa": "ui-shell-settings.ts",
      "titleEn": "ui-shell-settings.ts",
      "parentId": "concern-node:src-shared",
      "order": 6,
      "doc": { "constraints": [], "goals": [], "hints": [], "todos": [] },
      "links": [
        {
          "id": "link:shared:ui-shell-settings",
          "kind": "file",
          "label": "ui-shell-settings.ts",
          "target": "src/shared/ui-shell-settings.ts"
        }
      ]
    },
    {
      "id": "file:shared:ui-shell-settings-ipc",
      "kind": "issue",
      "titleJa": "ui-shell-settings-ipc.ts",
      "titleEn": "ui-shell-settings-ipc.ts",
      "parentId": "concern-node:src-shared",
      "order": 7,
      "doc": { "constraints": [], "goals": [], "hints": [], "todos": [] },
      "links": [
        {
          "id": "link:shared:ui-shell-settings-ipc",
          "kind": "file",
          "label": "ui-shell-settings-ipc.ts",
          "target": "src/shared/ui-shell-settings-ipc.ts"
        }
      ]
    },
    {
      "id": "file:adapters:desktop-api",
      "kind": "issue",
      "titleJa": "desktop-api.ts",
      "titleEn": "desktop-api.ts",
      "parentId": "concern-node:src-adapters",
      "order": 0,
      "doc": { "constraints": [], "goals": [], "hints": [], "todos": [] },
      "links": [
        {
          "id": "link:adapters:desktop-api",
          "kind": "file",
          "label": "desktop-api.ts",
          "target": "src/renderer/src/adapters/electron/desktop-api.ts"
        }
      ]
    },
    {
      "id": "file:adapters:runtime-diagnostics-source",
      "kind": "issue",
      "titleJa": "runtime-diagnostics-source.ts",
      "titleEn": "runtime-diagnostics-source.ts",
      "parentId": "concern-node:src-adapters",
      "order": 1,
      "doc": { "constraints": [], "goals": [], "hints": [], "todos": [] },
      "links": [
        {
          "id": "link:adapters:runtime-diagnostics-source",
          "kind": "file",
          "label": "runtime-diagnostics-source.ts",
          "target": "src/renderer/src/adapters/electron/runtime-diagnostics-source.ts"
        }
      ]
    },
    {
      "id": "file:bootstrap:mount-renderer",
      "kind": "issue",
      "titleJa": "mount-renderer.ts",
      "titleEn": "mount-renderer.ts",
      "parentId": "concern-node:src-bootstrap",
      "order": 0,
      "doc": { "constraints": [], "goals": [], "hints": [], "todos": [] },
      "links": [
        {
          "id": "link:bootstrap:mount-renderer",
          "kind": "file",
          "label": "mount-renderer.ts",
          "target": "src/renderer/src/bootstrap/mount-renderer.ts"
        }
      ]
    },
    {
      "id": "file:bootstrap:renderer-mode",
      "kind": "issue",
      "titleJa": "renderer-mode.ts",
      "titleEn": "renderer-mode.ts",
      "parentId": "concern-node:src-bootstrap",
      "order": 1,
      "doc": { "constraints": [], "goals": [], "hints": [], "todos": [] },
      "links": [
        {
          "id": "link:bootstrap:renderer-mode",
          "kind": "file",
          "label": "renderer-mode.ts",
          "target": "src/renderer/src/bootstrap/renderer-mode.ts"
        }
      ]
    },
    {
      "id": "file:bootstrap:resolve-renderer-root",
      "kind": "issue",
      "titleJa": "resolve-renderer-root.ts",
      "titleEn": "resolve-renderer-root.ts",
      "parentId": "concern-node:src-bootstrap",
      "order": 2,
      "doc": { "constraints": [], "goals": [], "hints": [], "todos": [] },
      "links": [
        {
          "id": "link:bootstrap:resolve-renderer-root",
          "kind": "file",
          "label": "resolve-renderer-root.ts",
          "target": "src/renderer/src/bootstrap/resolve-renderer-root.ts"
        }
      ]
    },
    {
      "id": "file:bootstrap:index",
      "kind": "issue",
      "titleJa": "index.ts (renderer)",
      "titleEn": "index.ts (renderer)",
      "parentId": "concern-node:src-bootstrap",
      "order": 3,
      "doc": { "constraints": [], "goals": [], "hints": [], "todos": [] },
      "links": [
        {
          "id": "link:bootstrap:index",
          "kind": "file",
          "label": "index.ts",
          "target": "src/renderer/src/index.ts"
        }
      ]
    },
    {
      "id": "file:catalog:component-catalog",
      "kind": "issue",
      "titleJa": "component-catalog.tsx",
      "titleEn": "component-catalog.tsx",
      "parentId": "concern-node:src-catalog",
      "order": 0,
      "doc": { "constraints": [], "goals": [], "hints": [], "todos": [] },
      "links": [
        {
          "id": "link:catalog:component-catalog",
          "kind": "file",
          "label": "component-catalog.tsx",
          "target": "src/renderer/src/catalog/component-catalog.tsx"
        }
      ]
    },
    {
      "id": "file:catalog:components-index",
      "kind": "issue",
      "titleJa": "components/index.tsx",
      "titleEn": "components/index.tsx",
      "parentId": "concern-node:src-catalog",
      "order": 1,
      "doc": { "constraints": [], "goals": [], "hints": [], "todos": [] },
      "links": [
        {
          "id": "link:catalog:components-index",
          "kind": "file",
          "label": "components/index.tsx",
          "target": "src/renderer/src/catalog/components/index.tsx"
        }
      ]
    },
    {
      "id": "file:catalog:components-content",
      "kind": "issue",
      "titleJa": "components/content.tsx",
      "titleEn": "components/content.tsx",
      "parentId": "concern-node:src-catalog",
      "order": 2,
      "doc": { "constraints": [], "goals": [], "hints": [], "todos": [] },
      "links": [
        {
          "id": "link:catalog:components-content",
          "kind": "file",
          "label": "components/content.tsx",
          "target": "src/renderer/src/catalog/components/content.tsx"
        }
      ]
    },
    {
      "id": "file:catalog:components-input",
      "kind": "issue",
      "titleJa": "components/input.tsx",
      "titleEn": "components/input.tsx",
      "parentId": "concern-node:src-catalog",
      "order": 3,
      "doc": { "constraints": [], "goals": [], "hints": [], "todos": [] },
      "links": [
        {
          "id": "link:catalog:components-input",
          "kind": "file",
          "label": "components/input.tsx",
          "target": "src/renderer/src/catalog/components/input.tsx"
        }
      ]
    },
    {
      "id": "file:catalog:components-media",
      "kind": "issue",
      "titleJa": "components/media.tsx",
      "titleEn": "components/media.tsx",
      "parentId": "concern-node:src-catalog",
      "order": 4,
      "doc": { "constraints": [], "goals": [], "hints": [], "todos": [] },
      "links": [
        {
          "id": "link:catalog:components-media",
          "kind": "file",
          "label": "components/media.tsx",
          "target": "src/renderer/src/catalog/components/media.tsx"
        }
      ]
    },
    {
      "id": "file:catalog:components-shared",
      "kind": "issue",
      "titleJa": "components/shared.tsx",
      "titleEn": "components/shared.tsx",
      "parentId": "concern-node:src-catalog",
      "order": 5,
      "doc": { "constraints": [], "goals": [], "hints": [], "todos": [] },
      "links": [
        {
          "id": "link:catalog:components-shared",
          "kind": "file",
          "label": "components/shared.tsx",
          "target": "src/renderer/src/catalog/components/shared.tsx"
        }
      ]
    },
    {
      "id": "file:catalog:components-structure",
      "kind": "issue",
      "titleJa": "components/structure.tsx",
      "titleEn": "components/structure.tsx",
      "parentId": "concern-node:src-catalog",
      "order": 6,
      "doc": { "constraints": [], "goals": [], "hints": [], "todos": [] },
      "links": [
        {
          "id": "link:catalog:components-structure",
          "kind": "file",
          "label": "components/structure.tsx",
          "target": "src/renderer/src/catalog/components/structure.tsx"
        }
      ]
    },
    {
      "id": "file:components:canvas",
      "kind": "issue",
      "titleJa": "canvas.tsx",
      "titleEn": "canvas.tsx",
      "parentId": "concern-node:src-components",
      "order": 0,
      "doc": { "constraints": [], "goals": [], "hints": [], "todos": [] },
      "links": [
        {
          "id": "link:components:canvas",
          "kind": "file",
          "label": "canvas.tsx",
          "target": "src/renderer/src/components/editor/canvas.tsx"
        }
      ]
    },
    {
      "id": "file:components:component-tree",
      "kind": "issue",
      "titleJa": "component-tree.tsx",
      "titleEn": "component-tree.tsx",
      "parentId": "concern-node:src-components",
      "order": 1,
      "doc": { "constraints": [], "goals": [], "hints": [], "todos": [] },
      "links": [
        {
          "id": "link:components:component-tree",
          "kind": "file",
          "label": "component-tree.tsx",
          "target": "src/renderer/src/components/editor/component-tree.tsx"
        }
      ]
    },
    {
      "id": "file:components:inspector",
      "kind": "issue",
      "titleJa": "inspector.tsx",
      "titleEn": "inspector.tsx",
      "parentId": "concern-node:src-components",
      "order": 2,
      "doc": { "constraints": [], "goals": [], "hints": [], "todos": [] },
      "links": [
        {
          "id": "link:components:inspector",
          "kind": "file",
          "label": "inspector.tsx",
          "target": "src/renderer/src/components/editor/inspector.tsx"
        }
      ]
    },
    {
      "id": "file:components:runtime-diagnostics-panel",
      "kind": "issue",
      "titleJa": "runtime-diagnostics-panel.tsx",
      "titleEn": "runtime-diagnostics-panel.tsx",
      "parentId": "concern-node:src-components",
      "order": 3,
      "doc": { "constraints": [], "goals": [], "hints": [], "todos": [] },
      "links": [
        {
          "id": "link:components:runtime-diagnostics-panel",
          "kind": "file",
          "label": "runtime-diagnostics-panel.tsx",
          "target": "src/renderer/src/components/editor/runtime-diagnostics-panel.tsx"
        }
      ]
    },
    {
      "id": "file:components:screen-inspector",
      "kind": "issue",
      "titleJa": "screen-inspector.tsx",
      "titleEn": "screen-inspector.tsx",
      "parentId": "concern-node:src-components",
      "order": 4,
      "doc": { "constraints": [], "goals": [], "hints": [], "todos": [] },
      "links": [
        {
          "id": "link:components:screen-inspector",
          "kind": "file",
          "label": "screen-inspector.tsx",
          "target": "src/renderer/src/components/editor/screen-inspector.tsx"
        }
      ]
    },
    {
      "id": "file:components:searchable-select",
      "kind": "issue",
      "titleJa": "searchable-select.tsx",
      "titleEn": "searchable-select.tsx",
      "parentId": "concern-node:src-components",
      "order": 5,
      "doc": { "constraints": [], "goals": [], "hints": [], "todos": [] },
      "links": [
        {
          "id": "link:components:searchable-select",
          "kind": "file",
          "label": "searchable-select.tsx",
          "target": "src/renderer/src/components/editor/searchable-select.tsx"
        }
      ]
    },
    {
      "id": "file:components:spec-node-editor",
      "kind": "issue",
      "titleJa": "spec-node-editor.tsx",
      "titleEn": "spec-node-editor.tsx",
      "parentId": "concern-node:src-components",
      "order": 6,
      "doc": { "constraints": [], "goals": [], "hints": [], "todos": [] },
      "links": [
        {
          "id": "link:components:spec-node-editor",
          "kind": "file",
          "label": "spec-node-editor.tsx",
          "target": "src/renderer/src/components/editor/spec-node-editor.tsx"
        }
      ]
    },
    {
      "id": "file:components:spec-outline-tree",
      "kind": "issue",
      "titleJa": "spec-outline-tree.tsx",
      "titleEn": "spec-outline-tree.tsx",
      "parentId": "concern-node:src-components",
      "order": 7,
      "doc": { "constraints": [], "goals": [], "hints": [], "todos": [] },
      "links": [
        {
          "id": "link:components:spec-outline-tree",
          "kind": "file",
          "label": "spec-outline-tree.tsx",
          "target": "src/renderer/src/components/editor/spec-outline-tree.tsx"
        }
      ]
    },
    {
      "id": "file:components:trace-link-inspector",
      "kind": "issue",
      "titleJa": "trace-link-inspector.tsx",
      "titleEn": "trace-link-inspector.tsx",
      "parentId": "concern-node:src-components",
      "order": 8,
      "doc": { "constraints": [], "goals": [], "hints": [], "todos": [] },
      "links": [
        {
          "id": "link:components:trace-link-inspector",
          "kind": "file",
          "label": "trace-link-inspector.tsx",
          "target": "src/renderer/src/components/editor/trace-link-inspector.tsx"
        }
      ]
    },
    {
      "id": "file:contracts:runtime-diagnostics",
      "kind": "issue",
      "titleJa": "runtime-diagnostics.ts",
      "titleEn": "runtime-diagnostics.ts",
      "parentId": "concern-node:src-contracts",
      "order": 0,
      "doc": { "constraints": [], "goals": [], "hints": [], "todos": [] },
      "links": [
        {
          "id": "link:contracts:runtime-diagnostics",
          "kind": "file",
          "label": "runtime-diagnostics.ts",
          "target": "src/renderer/src/contracts/runtime-diagnostics.ts"
        }
      ]
    },
    {
      "id": "file:contracts:runtime-diagnostics-source",
      "kind": "issue",
      "titleJa": "runtime-diagnostics-source.ts",
      "titleEn": "runtime-diagnostics-source.ts",
      "parentId": "concern-node:src-contracts",
      "order": 1,
      "doc": { "constraints": [], "goals": [], "hints": [], "todos": [] },
      "links": [
        {
          "id": "link:contracts:runtime-diagnostics-source",
          "kind": "file",
          "label": "runtime-diagnostics-source.ts",
          "target": "src/renderer/src/contracts/runtime-diagnostics-source.ts"
        }
      ]
    },
    {
      "id": "file:editor:canvas",
      "kind": "issue",
      "titleJa": "canvas.tsx",
      "titleEn": "canvas.tsx",
      "parentId": "concern-node:src-editor",
      "order": 0,
      "doc": { "constraints": [], "goals": [], "hints": [], "todos": [] },
      "links": [
        {
          "id": "link:editor:canvas",
          "kind": "file",
          "label": "canvas.tsx",
          "target": "src/renderer/src/editor/canvas.tsx"
        }
      ]
    },
    {
      "id": "file:editor:canvas-selection-state",
      "kind": "issue",
      "titleJa": "canvas-selection-state.ts",
      "titleEn": "canvas-selection-state.ts",
      "parentId": "concern-node:src-editor",
      "order": 1,
      "doc": { "constraints": [], "goals": [], "hints": [], "todos": [] },
      "links": [
        {
          "id": "link:editor:canvas-selection-state",
          "kind": "file",
          "label": "canvas-selection-state.ts",
          "target": "src/renderer/src/editor/canvas-selection-state.ts"
        }
      ]
    },
    {
      "id": "file:editor:component-outline-state",
      "kind": "issue",
      "titleJa": "component-outline-state.ts",
      "titleEn": "component-outline-state.ts",
      "parentId": "concern-node:src-editor",
      "order": 2,
      "doc": { "constraints": [], "goals": [], "hints": [], "todos": [] },
      "links": [
        {
          "id": "link:editor:component-outline-state",
          "kind": "file",
          "label": "component-outline-state.ts",
          "target": "src/renderer/src/editor/component-outline-state.ts"
        }
      ]
    },
    {
      "id": "file:editor:component-tree",
      "kind": "issue",
      "titleJa": "component-tree.tsx",
      "titleEn": "component-tree.tsx",
      "parentId": "concern-node:src-editor",
      "order": 3,
      "doc": { "constraints": [], "goals": [], "hints": [], "todos": [] },
      "links": [
        {
          "id": "link:editor:component-tree",
          "kind": "file",
          "label": "component-tree.tsx",
          "target": "src/renderer/src/editor/component-tree.tsx"
        }
      ]
    },
    {
      "id": "file:editor:editor-app",
      "kind": "issue",
      "titleJa": "editor-app.tsx",
      "titleEn": "editor-app.tsx",
      "parentId": "concern-node:src-editor",
      "order": 4,
      "doc": { "constraints": [], "goals": [], "hints": [], "todos": [] },
      "links": [
        {
          "id": "link:editor:editor-app",
          "kind": "file",
          "label": "editor-app.tsx",
          "target": "src/renderer/src/editor/editor-app.tsx"
        }
      ]
    },
    {
      "id": "file:editor:editor-state",
      "kind": "issue",
      "titleJa": "editor-state.ts",
      "titleEn": "editor-state.ts",
      "parentId": "concern-node:src-editor",
      "order": 5,
      "doc": { "constraints": [], "goals": [], "hints": [], "todos": [] },
      "links": [
        {
          "id": "link:editor:editor-state",
          "kind": "file",
          "label": "editor-state.ts",
          "target": "src/renderer/src/editor/editor-state.ts"
        }
      ]
    },
    {
      "id": "file:editor:inspector",
      "kind": "issue",
      "titleJa": "inspector.tsx",
      "titleEn": "inspector.tsx",
      "parentId": "concern-node:src-editor",
      "order": 6,
      "doc": { "constraints": [], "goals": [], "hints": [], "todos": [] },
      "links": [
        {
          "id": "link:editor:inspector",
          "kind": "file",
          "label": "inspector.tsx",
          "target": "src/renderer/src/editor/inspector.tsx"
        }
      ]
    },
    {
      "id": "file:editor:runtime-diagnostics-panel",
      "kind": "issue",
      "titleJa": "runtime-diagnostics-panel.tsx",
      "titleEn": "runtime-diagnostics-panel.tsx",
      "parentId": "concern-node:src-editor",
      "order": 7,
      "doc": { "constraints": [], "goals": [], "hints": [], "todos": [] },
      "links": [
        {
          "id": "link:editor:runtime-diagnostics-panel",
          "kind": "file",
          "label": "runtime-diagnostics-panel.tsx",
          "target": "src/renderer/src/editor/runtime-diagnostics-panel.tsx"
        }
      ]
    },
    {
      "id": "file:editor:searchable-select",
      "kind": "issue",
      "titleJa": "searchable-select.tsx",
      "titleEn": "searchable-select.tsx",
      "parentId": "concern-node:src-editor",
      "order": 8,
      "doc": { "constraints": [], "goals": [], "hints": [], "todos": [] },
      "links": [
        {
          "id": "link:editor:searchable-select",
          "kind": "file",
          "label": "searchable-select.tsx",
          "target": "src/renderer/src/editor/searchable-select.tsx"
        }
      ]
    },
    {
      "id": "file:interactions:canvas-selection",
      "kind": "issue",
      "titleJa": "canvas-selection.ts",
      "titleEn": "canvas-selection.ts",
      "parentId": "concern-node:src-interactions",
      "order": 0,
      "doc": { "constraints": [], "goals": [], "hints": [], "todos": [] },
      "links": [
        {
          "id": "link:interactions:canvas-selection",
          "kind": "file",
          "label": "canvas-selection.ts",
          "target": "src/renderer/src/interactions/editor/canvas-selection.ts"
        }
      ]
    },
    {
      "id": "file:interactions:component-outline",
      "kind": "issue",
      "titleJa": "component-outline.ts",
      "titleEn": "component-outline.ts",
      "parentId": "concern-node:src-interactions",
      "order": 1,
      "doc": { "constraints": [], "goals": [], "hints": [], "todos": [] },
      "links": [
        {
          "id": "link:interactions:component-outline",
          "kind": "file",
          "label": "component-outline.ts",
          "target": "src/renderer/src/interactions/editor/component-outline.ts"
        }
      ]
    },
    {
      "id": "file:screens:editor-screen",
      "kind": "issue",
      "titleJa": "editor-screen.tsx",
      "titleEn": "editor-screen.tsx",
      "parentId": "concern-node:src-screens",
      "order": 0,
      "doc": { "constraints": [], "goals": [], "hints": [], "todos": [] },
      "links": [
        {
          "id": "link:screens:editor-screen",
          "kind": "file",
          "label": "editor-screen.tsx",
          "target": "src/renderer/src/screens/editor/editor-screen.tsx"
        }
      ]
    },
    {
      "id": "file:spec:editor-document",
      "kind": "issue",
      "titleJa": "editor-document.ts",
      "titleEn": "editor-document.ts",
      "parentId": "concern-node:src-spec",
      "order": 0,
      "doc": { "constraints": [], "goals": [], "hints": [], "todos": [] },
      "links": [
        {
          "id": "link:spec:editor-document",
          "kind": "file",
          "label": "editor-document.ts",
          "target": "src/renderer/src/spec/editor-document.ts"
        }
      ]
    },
    {
      "id": "file:spec:editor-schema",
      "kind": "issue",
      "titleJa": "editor-schema.ts",
      "titleEn": "editor-schema.ts",
      "parentId": "concern-node:src-spec",
      "order": 1,
      "doc": { "constraints": [], "goals": [], "hints": [], "todos": [] },
      "links": [
        {
          "id": "link:spec:editor-schema",
          "kind": "file",
          "label": "editor-schema.ts",
          "target": "src/renderer/src/spec/editor-schema.ts"
        }
      ]
    },
    {
      "id": "file:spec:surface-context",
      "kind": "issue",
      "titleJa": "surface-context.ts",
      "titleEn": "surface-context.ts",
      "parentId": "concern-node:src-spec",
      "order": 2,
      "doc": { "constraints": [], "goals": [], "hints": [], "todos": [] },
      "links": [
        {
          "id": "link:spec:surface-context",
          "kind": "file",
          "label": "surface-context.ts",
          "target": "src/renderer/src/spec/surface-context.ts"
        }
      ]
    },
    {
      "id": "file:spec:default-document",
      "kind": "issue",
      "titleJa": "editor-document/default-document.ts",
      "titleEn": "editor-document/default-document.ts",
      "parentId": "concern-node:src-spec",
      "order": 3,
      "doc": { "constraints": [], "goals": [], "hints": [], "todos": [] },
      "links": [
        {
          "id": "link:spec:default-document",
          "kind": "file",
          "label": "default-document.ts",
          "target": "src/renderer/src/spec/editor-document/default-document.ts"
        }
      ]
    },
    {
      "id": "file:spec:normalization",
      "kind": "issue",
      "titleJa": "editor-document/normalization.ts",
      "titleEn": "editor-document/normalization.ts",
      "parentId": "concern-node:src-spec",
      "order": 4,
      "doc": { "constraints": [], "goals": [], "hints": [], "todos": [] },
      "links": [
        {
          "id": "link:spec:normalization",
          "kind": "file",
          "label": "normalization.ts",
          "target": "src/renderer/src/spec/editor-document/normalization.ts"
        }
      ]
    },
    {
      "id": "file:spec:prompt-export",
      "kind": "issue",
      "titleJa": "editor-document/prompt-export.ts",
      "titleEn": "editor-document/prompt-export.ts",
      "parentId": "concern-node:src-spec",
      "order": 5,
      "doc": { "constraints": [], "goals": [], "hints": [], "todos": [] },
      "links": [
        {
          "id": "link:spec:prompt-export",
          "kind": "file",
          "label": "prompt-export.ts",
          "target": "src/renderer/src/spec/editor-document/prompt-export.ts"
        }
      ]
    },
    {
      "id": "file:spec:spec-nodes",
      "kind": "issue",
      "titleJa": "editor-document/spec-nodes.ts",
      "titleEn": "editor-document/spec-nodes.ts",
      "parentId": "concern-node:src-spec",
      "order": 6,
      "doc": { "constraints": [], "goals": [], "hints": [], "todos": [] },
      "links": [
        {
          "id": "link:spec:spec-nodes",
          "kind": "file",
          "label": "spec-nodes.ts",
          "target": "src/renderer/src/spec/editor-document/spec-nodes.ts"
        }
      ]
    },
    {
      "id": "file:spec:tree",
      "kind": "issue",
      "titleJa": "editor-document/tree.ts",
      "titleEn": "editor-document/tree.ts",
      "parentId": "concern-node:src-spec",
      "order": 7,
      "doc": { "constraints": [], "goals": [], "hints": [], "todos": [] },
      "links": [
        {
          "id": "link:spec:tree",
          "kind": "file",
          "label": "tree.ts",
          "target": "src/renderer/src/spec/editor-document/tree.ts"
        }
      ]
    },
    {
      "id": "file:spec:validation",
      "kind": "issue",
      "titleJa": "editor-document/validation.ts",
      "titleEn": "editor-document/validation.ts",
      "parentId": "concern-node:src-spec",
      "order": 8,
      "doc": { "constraints": [], "goals": [], "hints": [], "todos": [] },
      "links": [
        {
          "id": "link:spec:validation",
          "kind": "file",
          "label": "validation.ts",
          "target": "src/renderer/src/spec/editor-document/validation.ts"
        }
      ]
    },
    {
      "id": "file:state:runtime-view-model",
      "kind": "issue",
      "titleJa": "runtime-view-model.ts",
      "titleEn": "runtime-view-model.ts",
      "parentId": "concern-node:src-state",
      "order": 0,
      "doc": { "constraints": [], "goals": [], "hints": [], "todos": [] },
      "links": [
        {
          "id": "link:state:runtime-view-model",
          "kind": "file",
          "label": "runtime-view-model.ts",
          "target": "src/renderer/src/state/runtime-view-model.ts"
        }
      ]
    },
    {
      "id": "file:state:timestamp-display",
      "kind": "issue",
      "titleJa": "timestamp-display.ts",
      "titleEn": "timestamp-display.ts",
      "parentId": "concern-node:src-state",
      "order": 1,
      "doc": { "constraints": [], "goals": [], "hints": [], "todos": [] },
      "links": [
        {
          "id": "link:state:timestamp-display",
          "kind": "file",
          "label": "timestamp-display.ts",
          "target": "src/renderer/src/state/timestamp-display.ts"
        }
      ]
    },
    {
      "id": "file:state:component-state",
      "kind": "issue",
      "titleJa": "editor/component-state.ts",
      "titleEn": "editor/component-state.ts",
      "parentId": "concern-node:src-state",
      "order": 2,
      "doc": { "constraints": [], "goals": [], "hints": [], "todos": [] },
      "links": [
        {
          "id": "link:state:component-state",
          "kind": "file",
          "label": "editor/component-state.ts",
          "target": "src/renderer/src/state/editor/component-state.ts"
        }
      ]
    },
    {
      "id": "file:state:document-options",
      "kind": "issue",
      "titleJa": "editor/document-options.ts",
      "titleEn": "editor/document-options.ts",
      "parentId": "concern-node:src-state",
      "order": 3,
      "doc": { "constraints": [], "goals": [], "hints": [], "todos": [] },
      "links": [
        {
          "id": "link:state:document-options",
          "kind": "file",
          "label": "editor/document-options.ts",
          "target": "src/renderer/src/state/editor/document-options.ts"
        }
      ]
    },
    {
      "id": "file:state:editor-index",
      "kind": "issue",
      "titleJa": "editor/index.ts",
      "titleEn": "editor/index.ts",
      "parentId": "concern-node:src-state",
      "order": 4,
      "doc": { "constraints": [], "goals": [], "hints": [], "todos": [] },
      "links": [
        {
          "id": "link:state:editor-index",
          "kind": "file",
          "label": "editor/index.ts",
          "target": "src/renderer/src/state/editor/index.ts"
        }
      ]
    },
    {
      "id": "file:state:layout-constraints",
      "kind": "issue",
      "titleJa": "editor/layout-constraints.ts",
      "titleEn": "editor/layout-constraints.ts",
      "parentId": "concern-node:src-state",
      "order": 5,
      "doc": { "constraints": [], "goals": [], "hints": [], "todos": [] },
      "links": [
        {
          "id": "link:state:layout-constraints",
          "kind": "file",
          "label": "editor/layout-constraints.ts",
          "target": "src/renderer/src/state/editor/layout-constraints.ts"
        }
      ]
    },
    {
      "id": "file:state:spec-node-state",
      "kind": "issue",
      "titleJa": "editor/spec-node-state.ts",
      "titleEn": "editor/spec-node-state.ts",
      "parentId": "concern-node:src-state",
      "order": 6,
      "doc": { "constraints": [], "goals": [], "hints": [], "todos": [] },
      "links": [
        {
          "id": "link:state:spec-node-state",
          "kind": "file",
          "label": "editor/spec-node-state.ts",
          "target": "src/renderer/src/state/editor/spec-node-state.ts"
        }
      ]
    },
    {
      "id": "file:state:viewport-state",
      "kind": "issue",
      "titleJa": "editor/viewport-state.ts",
      "titleEn": "editor/viewport-state.ts",
      "parentId": "concern-node:src-state",
      "order": 7,
      "doc": { "constraints": [], "goals": [], "hints": [], "todos": [] },
      "links": [
        {
          "id": "link:state:viewport-state",
          "kind": "file",
          "label": "editor/viewport-state.ts",
          "target": "src/renderer/src/state/editor/viewport-state.ts"
        }
      ]
    }
  ]
}
